agent_resources/__init__.py
agent_resources/exceptions.py
agent_resources/fetcher.py
agent_resources/github.py
agent_resources/scaffold.py
agent_resources/cli/__init__.py
agent_resources/cli/agent.py
agent_resources/cli/command.py
agent_resources/cli/common.py
agent_resources/cli/create.py
agent_resources/cli/skill.py
agent_resources-0.3.1.dist-info/METADATA
agent_resources-0.3.1.dist-info/WHEEL
agent_resources-0.3.1.dist-info/entry_points.txt
agent_resources-0.3.1.dist-info/RECORD
